mpl_converter/__init__.py
mpl_converter/matplotlib.py
mpl_converter/monkey_patch.py
mpl_converter/utils.py
plotly_converter/__init__.py
plotly_converter/plotly.py
plotly_converter/plotly_browser_adapter.py
plotly_converter/plotly_browser_adapter_old.py
plotly_converter/plotly_stub.py
plotly_converter/utils.py
plt_checker/__init__.py
plt_checker/atomic_methods.py
plt_checker/core.py
plt_checker/exceptions.py
plt_checker/match_meshes.py
Universal_Chart_Grader-1.1.0.dist-info/METADATA
Universal_Chart_Grader-1.1.0.dist-info/WHEEL
Universal_Chart_Grader-1.1.0.dist-info/entry_points.txt
Universal_Chart_Grader-1.1.0.dist-info/top_level.txt
Universal_Chart_Grader-1.1.0.dist-info/RECORD
