Metadata-Version: 2.1
Name: Universal-Chart-Grader
Version: 1.1.0
Summary: UNKNOWN
Home-page: UNKNOWN
License: UNKNOWN
Platform: UNKNOWN
Requires-Dist: numpy
Requires-Dist: matplotlib
Requires-Dist: scipy
Requires-Dist: dill
Requires-Dist: wrapt
